[
    {
        "driver": "V. BOTTAS",
        "km/h": 332.6,
        "gp": "Russian GP",
        "year": 2014
    },
    {
        "driver": "K. MAGNUSSEN",
        "km/h": 328.3,
        "gp": "Russian GP",
        "year": 2014
    },
    {
        "driver": "N. HULKENBERG",
        "km/h": 327.7,
        "gp": "Russian GP",
        "year": 2014
    },
    {
        "driver": "J. BUTTON",
        "km/h": 327.6,
        "gp": "Russian GP",
        "year": 2014
    },
    {
        "driver": "L. HAMILTON",
        "km/h": 327.3,
        "gp": "Russian GP",
        "year": 2014
    },
    {
        "driver": "D. KVYAT",
        "km/h": 327.1,
        "gp": "Russian GP",
        "year": 2014
    },
    {
        "driver": "N. ROSBERG",
        "km/h": 327.0,
        "gp": "Russian GP",
        "year": 2014
    },
    {
        "driver": "S. PEREZ",
        "km/h": 325.9,
        "gp": "Russian GP",
        "year": 2014
    },
    {
        "driver": "J. VERGNE",
        "km/h": 325.4,
        "gp": "Russian GP",
        "year": 2014
    },
    {
        "driver": "A. SUTIL",
        "km/h": 323.6,
        "gp": "Russian GP",
        "year": 2014
    },
    {
        "driver": "E. GUTIERREZ",
        "km/h": 322.9,
        "gp": "Russian GP",
        "year": 2014
    },
    {
        "driver": "K. RAIKKONEN",
        "km/h": 322.7,
        "gp": "Russian GP",
        "year": 2014
    },
    {
        "driver": "F. ALONSO",
        "km/h": 322.5,
        "gp": "Russian GP",
        "year": 2014
    },
    {
        "driver": "R. GROSJEAN",
        "km/h": 322.3,
        "gp": "Russian GP",
        "year": 2014
    },
    {
        "driver": "S. VETTEL",
        "km/h": 321.7,
        "gp": "Russian GP",
        "year": 2014
    },
    {
        "driver": "D. RICCIARDO",
        "km/h": 321.2,
        "gp": "Russian GP",
        "year": 2014
    },
    {
        "driver": "M. ERICSSON",
        "km/h": 319.8,
        "gp": "Russian GP",
        "year": 2014
    },
    {
        "driver": "K. KOBAYASHI",
        "km/h": 319.2,
        "gp": "Russian GP",
        "year": 2014
    },
    {
        "driver": "P. MALDONADO",
        "km/h": 317.6,
        "gp": "Russian GP",
        "year": 2014
    },
    {
        "driver": "M. CHILTON",
        "km/h": 312.5,
        "gp": "Russian GP",
        "year": 2014
    },
    {
        "driver": "F. MASSA",
        "km/h": 309.2,
        "gp": "Russian GP",
        "year": 2014
    }
]