[
    {
        "driver": "F. MASSA",
        "km/h": 327.5,
        "gp": "Austrian GP",
        "year": 2014
    },
    {
        "driver": "V. BOTTAS",
        "km/h": 323.1,
        "gp": "Austrian GP",
        "year": 2014
    },
    {
        "driver": "S. PEREZ",
        "km/h": 322.7,
        "gp": "Austrian GP",
        "year": 2014
    },
    {
        "driver": "L. HAMILTON",
        "km/h": 321.4,
        "gp": "Austrian GP",
        "year": 2014
    },
    {
        "driver": "N. HULKENBERG",
        "km/h": 321.1,
        "gp": "Austrian GP",
        "year": 2014
    },
    {
        "driver": "J. BUTTON",
        "km/h": 320.2,
        "gp": "Austrian GP",
        "year": 2014
    },
    {
        "driver": "N. ROSBERG",
        "km/h": 320.0,
        "gp": "Austrian GP",
        "year": 2014
    },
    {
        "driver": "K. MAGNUSSEN",
        "km/h": 319.6,
        "gp": "Austrian GP",
        "year": 2014
    },
    {
        "driver": "K. RAIKKONEN",
        "km/h": 319.2,
        "gp": "Austrian GP",
        "year": 2014
    },
    {
        "driver": "J. VERGNE",
        "km/h": 319.1,
        "gp": "Austrian GP",
        "year": 2014
    },
    {
        "driver": "F. ALONSO",
        "km/h": 317.3,
        "gp": "Austrian GP",
        "year": 2014
    },
    {
        "driver": "D. KVYAT",
        "km/h": 317.1,
        "gp": "Austrian GP",
        "year": 2014
    },
    {
        "driver": "A. SUTIL",
        "km/h": 315.5,
        "gp": "Austrian GP",
        "year": 2014
    },
    {
        "driver": "P. MALDONADO",
        "km/h": 314.3,
        "gp": "Austrian GP",
        "year": 2014
    },
    {
        "driver": "E. GUTIERREZ",
        "km/h": 314.2,
        "gp": "Austrian GP",
        "year": 2014
    },
    {
        "driver": "D. RICCIARDO",
        "km/h": 312.7,
        "gp": "Austrian GP",
        "year": 2014
    },
    {
        "driver": "S. VETTEL",
        "km/h": 312.6,
        "gp": "Austrian GP",
        "year": 2014
    },
    {
        "driver": "K. KOBAYASHI",
        "km/h": 311.6,
        "gp": "Austrian GP",
        "year": 2014
    },
    {
        "driver": "R. GROSJEAN",
        "km/h": 311.3,
        "gp": "Austrian GP",
        "year": 2014
    },
    {
        "driver": "M. CHILTON",
        "km/h": 309.8,
        "gp": "Austrian GP",
        "year": 2014
    },
    {
        "driver": "J. BIANCHI",
        "km/h": 309.6,
        "gp": "Austrian GP",
        "year": 2014
    },
    {
        "driver": "M. ERICSSON",
        "km/h": 309.2,
        "gp": "Austrian GP",
        "year": 2014
    }
]